FastRDB/__init__.py
FastRDB/crud.py
fast_rdb-0.0.2.dist-info/METADATA
fast_rdb-0.0.2.dist-info/WHEEL
fast_rdb-0.0.2.dist-info/RECORD
