Metadata-Version: 2.3
Name: fast-rdb
Version: 0.0.2
Summary: A high-performance, generic CRUD operations package combining SQLAlchemy async ORM with Redis caching. Features type-safe CRUD operations, automatic cache invalidation, pagination support, and Pydantic integration for schema validation. Ideal for FastAPI backends and read-heavy applications requiring optimized database access.
License: MIT
Keywords: fastapi,crud,async,sqlalchemy,redis,cache,pydantic
Author: Biisal
Author-email: biisal.int@gmail.com
Requires-Python: >=3.10,<4.0
Classifier: Development Status :: 3 - Alpha
Classifier: Framework :: AsyncIO
Classifier: Intended Audience :: Developers
Classifier: License :: OSI Approved :: MIT License
Classifier: Operating System :: OS Independent
Classifier: Programming Language :: Python :: 3
Classifier: Programming Language :: Python :: 3.10
Classifier: Programming Language :: Python :: 3.11
Classifier: Programming Language :: Python :: 3.12
Classifier: Programming Language :: Python :: 3.13
Classifier: Topic :: Software Development :: Libraries
Classifier: Typing :: Typed
Requires-Dist: SQLAlchemy (>=2.0.0,<3.0.0)
Requires-Dist: orjson (>=3.9,<4.0)
Requires-Dist: pydantic (>=2.0,<3.0)
Requires-Dist: redis (>=5.0,<6.0)
Requires-Dist: sqlalchemy-utils (>=0.41.1,<0.42.0)
Project-URL: Repository, https://github.com/biisal/FastRDB
